{"!":"com.github.javaparser.ast.CompilationUnit","range":{"beginLine":1,"beginColumn":1,"endLine":44,"endColumn":2},"tokenRange":{"beginToken":{"kind":19,"text":"class"},"endToken":{"kind":0,"text":""}},"imports":[],"types":[{"!":"com.github.javaparser.ast.body.ClassOrInterfaceDeclaration","range":{"beginLine":1,"beginColumn":1,"endLine":44,"endColumn":2},"tokenRange":{"beginToken":{"kind":19,"text":"class"},"endToken":{"kind":100,"text":"}"}},"extendedTypes":[],"implementedTypes":[],"isInterface":"false","typeParameters":[],"members":[{"!":"com.github.javaparser.ast.body.MethodDeclaration","range":{"beginLine":2,"beginColumn":1,"endLine":42,"endColumn":2},"tokenRange":{"beginToken":{"kind":107,"text":"@"},"endToken":{"kind":100,"text":"}"}},"body":{"!":"com.github.javaparser.ast.stmt.BlockStmt","range":{"beginLine":4,"beginColumn":25,"endLine":42,"endColumn":2},"tokenRange":{"beginToken":{"kind":99,"text":"{"},"endToken":{"kind":100,"text":"}"}},"statements":[{"!":"com.github.javaparser.ast.stmt.ExpressionStmt","range":{"beginLine":5,"beginColumn":3,"endLine":5,"endColumn":40},"tokenRange":{"beginToken":{"kind":94,"text":"EntityManager"},"endToken":{"kind":103,"text":";"}},"expression":{"!":"com.github.javaparser.ast.expr.VariableDeclarationExpr","range":{"beginLine":5,"beginColumn":3,"endLine":5,"endColumn":39},"tokenRange":{"beginToken":{"kind":94,"text":"EntityManager"},"endToken":{"kind":98,"text":")"}},"annotations":[],"modifiers":[],"variables":[{"!":"com.github.javaparser.ast.body.VariableDeclarator","range":{"beginLine":5,"beginColumn":17,"endLine":5,"endColumn":39},"tokenRange":{"beginToken":{"kind":94,"text":"em"},"endToken":{"kind":98,"text":")"}},"initializer":{"!":"com.github.javaparser.ast.expr.MethodCallExpr","range":{"beginLine":5,"beginColumn":22,"endLine":5,"endColumn":39},"tokenRange":{"beginToken":{"kind":94,"text":"getEntityManager"},"endToken":{"kind":98,"text":")"}},"arguments":[],"name":{"!":"com.github.javaparser.ast.expr.SimpleName","range":{"beginLine":5,"beginColumn":22,"endLine":5,"endColumn":37},"tokenRange":{"beginToken":{"kind":94,"text":"getEntityManager"},"endToken":{"kind":94,"text":"getEntityManager"}},"identifier":"getEntityManager"}},"name":{"!":"com.github.javaparser.ast.expr.SimpleName","range":{"beginLine":5,"beginColumn":17,"endLine":5,"endColumn":18},"tokenRange":{"beginToken":{"kind":94,"text":"em"},"endToken":{"kind":94,"text":"em"}},"identifier":"em"},"type":{"!":"com.github.javaparser.ast.type.ClassOrInterfaceType","range":{"beginLine":5,"beginColumn":3,"endLine":5,"endColumn":15},"tokenRange":{"beginToken":{"kind":94,"text":"EntityManager"},"endToken":{"kind":94,"text":"EntityManager"}},"name":{"!":"com.github.javaparser.ast.expr.SimpleName","range":{"beginLine":5,"beginColumn":3,"endLine":5,"endColumn":15},"tokenRange":{"beginToken":{"kind":94,"text":"EntityManager"},"endToken":{"kind":94,"text":"EntityManager"}},"identifier":"EntityManager"},"annotations":[]}}]}},{"!":"com.github.javaparser.ast.stmt.ExpressionStmt","range":{"beginLine":7,"beginColumn":3,"endLine":7,"endColumn":59},"tokenRange":{"beginToken":{"kind":94,"text":"EmbeddableListEntity1"},"endToken":{"kind":103,"text":";"}},"expression":{"!":"com.github.javaparser.ast.expr.VariableDeclarationExpr","range":{"beginLine":7,"beginColumn":3,"endLine":7,"endColumn":58},"tokenRange":{"beginToken":{"kind":94,"text":"EmbeddableListEntity1"},"endToken":{"kind":98,"text":")"}},"annotations":[],"modifiers":[],"variables":[{"!":"com.github.javaparser.ast.body.VariableDeclarator","range":{"beginLine":7,"beginColumn":25,"endLine":7,"endColumn":58},"tokenRange":{"beginToken":{"kind":94,"text":"ele1"},"endToken":{"kind":98,"text":")"}},"initializer":{"!":"com.github.javaparser.ast.expr.ObjectCreationExpr","range":{"beginLine":7,"beginColumn":32,"endLine":7,"endColumn":58},"tokenRange":{"beginToken":{"kind":42,"text":"new"},"endToken":{"kind":98,"text":")"}},"arguments":[],"type":{"!":"com.github.javaparser.ast.type.ClassOrInterfaceType","range":{"beginLine":7,"beginColumn":36,"endLine":7,"endColumn":56},"tokenRange":{"beginToken":{"kind":94,"text":"EmbeddableListEntity1"},"endToken":{"kind":94,"text":"EmbeddableListEntity1"}},"name":{"!":"com.github.javaparser.ast.expr.SimpleName","range":{"beginLine":7,"beginColumn":36,"endLine":7,"endColumn":56},"tokenRange":{"beginToken":{"kind":94,"text":"EmbeddableListEntity1"},"endToken":{"kind":94,"text":"EmbeddableListEntity1"}},"identifier":"EmbeddableListEntity1"},"annotations":[]}},"name":{"!":"com.github.javaparser.ast.expr.SimpleName","range":{"beginLine":7,"beginColumn":25,"endLine":7,"endColumn":28},"tokenRange":{"beginToken":{"kind":94,"text":"ele1"},"endToken":{"kind":94,"text":"ele1"}},"identifier":"ele1"},"type":{"!":"com.github.javaparser.ast.type.ClassOrInterfaceType","range":{"beginLine":7,"beginColumn":3,"endLine":7,"endColumn":23},"tokenRange":{"beginToken":{"kind":94,"text":"EmbeddableListEntity1"},"endToken":{"kind":94,"text":"EmbeddableListEntity1"}},"name":{"!":"com.github.javaparser.ast.expr.SimpleName","range":{"beginLine":7,"beginColumn":3,"endLine":7,"endColumn":23},"tokenRange":{"beginToken":{"kind":94,"text":"EmbeddableListEntity1"},"endToken":{"kind":94,"text":"EmbeddableListEntity1"}},"identifier":"EmbeddableListEntity1"},"annotations":[]}}]}},{"!":"com.github.javaparser.ast.stmt.ExpressionStmt","range":{"beginLine":10,"beginColumn":3,"endLine":10,"endColumn":30},"tokenRange":{"beginToken":{"kind":94,"text":"em"},"endToken":{"kind":103,"text":";"}},"expression":{"!":"com.github.javaparser.ast.expr.MethodCallExpr","range":{"beginLine":10,"beginColumn":3,"endLine":10,"endColumn":29},"tokenRange":{"beginToken":{"kind":94,"text":"em"},"endToken":{"kind":98,"text":")"}},"arguments":[],"name":{"!":"com.github.javaparser.ast.expr.SimpleName","range":{"beginLine":10,"beginColumn":23,"endLine":10,"endColumn":27},"tokenRange":{"beginToken":{"kind":94,"text":"begin"},"endToken":{"kind":94,"text":"begin"}},"identifier":"begin"},"scope":{"!":"com.github.javaparser.ast.expr.MethodCallExpr","range":{"beginLine":10,"beginColumn":3,"endLine":10,"endColumn":21},"tokenRange":{"beginToken":{"kind":94,"text":"em"},"endToken":{"kind":98,"text":")"}},"arguments":[],"name":{"!":"com.github.javaparser.ast.expr.SimpleName","range":{"beginLine":10,"beginColumn":6,"endLine":10,"endColumn":19},"tokenRange":{"beginToken":{"kind":94,"text":"getTransaction"},"endToken":{"kind":94,"text":"getTransaction"}},"identifier":"getTransaction"},"scope":{"!":"com.github.javaparser.ast.expr.NameExpr","range":{"beginLine":10,"beginColumn":3,"endLine":10,"endColumn":4},"tokenRange":{"beginToken":{"kind":94,"text":"em"},"endToken":{"kind":94,"text":"em"}},"name":{"!":"com.github.javaparser.ast.expr.SimpleName","range":{"beginLine":10,"beginColumn":3,"endLine":10,"endColumn":4},"tokenRange":{"beginToken":{"kind":94,"text":"em"},"endToken":{"kind":94,"text":"em"}},"identifier":"em"}}}},"comment":{"!":"com.github.javaparser.ast.comments.LineComment","range":{"beginLine":9,"beginColumn":3,"endLine":9,"endColumn":63},"tokenRange":{"beginToken":{"kind":5,"text":"// Revision 1 (ele1: initially 1 element in both collections)"},"endToken":{"kind":5,"text":"// Revision 1 (ele1: initially 1 element in both collections)"}},"content":" Revision 1 (ele1: initially 1 element in both collections)"}},{"!":"com.github.javaparser.ast.stmt.ExpressionStmt","range":{"beginLine":11,"beginColumn":3,"endLine":11,"endColumn":38},"tokenRange":{"beginToken":{"kind":94,"text":"ele1"},"endToken":{"kind":103,"text":";"}},"expression":{"!":"com.github.javaparser.ast.expr.MethodCallExpr","range":{"beginLine":11,"beginColumn":3,"endLine":11,"endColumn":37},"tokenRange":{"beginToken":{"kind":94,"text":"ele1"},"endToken":{"kind":98,"text":")"}},"arguments":[{"!":"com.github.javaparser.ast.expr.NameExpr","range":{"beginLine":11,"beginColumn":32,"endLine":11,"endColumn":35},"tokenRange":{"beginToken":{"kind":94,"text":"c3_1"},"endToken":{"kind":94,"text":"c3_1"}},"name":{"!":"com.github.javaparser.ast.expr.SimpleName","range":{"beginLine":11,"beginColumn":32,"endLine":11,"endColumn":35},"tokenRange":{"beginToken":{"kind":94,"text":"c3_1"},"endToken":{"kind":94,"text":"c3_1"}},"identifier":"c3_1"}}],"name":{"!":"com.github.javaparser.ast.expr.SimpleName","range":{"beginLine":11,"beginColumn":27,"endLine":11,"endColumn":29},"tokenRange":{"beginToken":{"kind":94,"text":"add"},"endToken":{"kind":94,"text":"add"}},"identifier":"add"},"scope":{"!":"com.github.javaparser.ast.expr.MethodCallExpr","range":{"beginLine":11,"beginColumn":3,"endLine":11,"endColumn":25},"tokenRange":{"beginToken":{"kind":94,"text":"ele1"},"endToken":{"kind":98,"text":")"}},"arguments":[],"name":{"!":"com.github.javaparser.ast.expr.SimpleName","range":{"beginLine":11,"beginColumn":8,"endLine":11,"endColumn":23},"tokenRange":{"beginToken":{"kind":94,"text":"getComponentList"},"endToken":{"kind":94,"text":"getComponentList"}},"identifier":"getComponentList"},"scope":{"!":"com.github.javaparser.ast.expr.NameExpr","range":{"beginLine":11,"beginColumn":3,"endLine":11,"endColumn":6},"tokenRange":{"beginToken":{"kind":94,"text":"ele1"},"endToken":{"kind":94,"text":"ele1"}},"name":{"!":"com.github.javaparser.ast.expr.SimpleName","range":{"beginLine":11,"beginColumn":3,"endLine":11,"endColumn":6},"tokenRange":{"beginToken":{"kind":94,"text":"ele1"},"endToken":{"kind":94,"text":"ele1"}},"identifier":"ele1"}}}}},{"!":"com.github.javaparser.ast.stmt.ExpressionStmt","range":{"beginLine":12,"beginColumn":3,"endLine":12,"endColumn":21},"tokenRange":{"beginToken":{"kind":94,"text":"em"},"endToken":{"kind":103,"text":";"}},"expression":{"!":"com.github.javaparser.ast.expr.MethodCallExpr","range":{"beginLine":12,"beginColumn":3,"endLine":12,"endColumn":20},"tokenRange":{"beginToken":{"kind":94,"text":"em"},"endToken":{"kind":98,"text":")"}},"arguments":[{"!":"com.github.javaparser.ast.expr.NameExpr","range":{"beginLine":12,"beginColumn":15,"endLine":12,"endColumn":18},"tokenRange":{"beginToken":{"kind":94,"text":"ele1"},"endToken":{"kind":94,"text":"ele1"}},"name":{"!":"com.github.javaparser.ast.expr.SimpleName","range":{"beginLine":12,"beginColumn":15,"endLine":12,"endColumn":18},"tokenRange":{"beginToken":{"kind":94,"text":"ele1"},"endToken":{"kind":94,"text":"ele1"}},"identifier":"ele1"}}],"name":{"!":"com.github.javaparser.ast.expr.SimpleName","range":{"beginLine":12,"beginColumn":6,"endLine":12,"endColumn":12},"tokenRange":{"beginToken":{"kind":94,"text":"persist"},"endToken":{"kind":94,"text":"persist"}},"identifier":"persist"},"scope":{"!":"com.github.javaparser.ast.expr.NameExpr","range":{"beginLine":12,"beginColumn":3,"endLine":12,"endColumn":4},"tokenRange":{"beginToken":{"kind":94,"text":"em"},"endToken":{"kind":94,"text":"em"}},"name":{"!":"com.github.javaparser.ast.expr.SimpleName","range":{"beginLine":12,"beginColumn":3,"endLine":12,"endColumn":4},"tokenRange":{"beginToken":{"kind":94,"text":"em"},"endToken":{"kind":94,"text":"em"}},"identifier":"em"}}}},{"!":"com.github.javaparser.ast.stmt.ExpressionStmt","range":{"beginLine":13,"beginColumn":3,"endLine":13,"endColumn":31},"tokenRange":{"beginToken":{"kind":94,"text":"em"},"endToken":{"kind":103,"text":";"}},"expression":{"!":"com.github.javaparser.ast.expr.MethodCallExpr","range":{"beginLine":13,"beginColumn":3,"endLine":13,"endColumn":30},"tokenRange":{"beginToken":{"kind":94,"text":"em"},"endToken":{"kind":98,"text":")"}},"arguments":[],"name":{"!":"com.github.javaparser.ast.expr.SimpleName","range":{"beginLine":13,"beginColumn":23,"endLine":13,"endColumn":28},"tokenRange":{"beginToken":{"kind":94,"text":"commit"},"endToken":{"kind":94,"text":"commit"}},"identifier":"commit"},"scope":{"!":"com.github.javaparser.ast.expr.MethodCallExpr","range":{"beginLine":13,"beginColumn":3,"endLine":13,"endColumn":21},"tokenRange":{"beginToken":{"kind":94,"text":"em"},"endToken":{"kind":98,"text":")"}},"arguments":[],"name":{"!":"com.github.javaparser.ast.expr.SimpleName","range":{"beginLine":13,"beginColumn":6,"endLine":13,"endColumn":19},"tokenRange":{"beginToken":{"kind":94,"text":"getTransaction"},"endToken":{"kind":94,"text":"getTransaction"}},"identifier":"getTransaction"},"scope":{"!":"com.github.javaparser.ast.expr.NameExpr","range":{"beginLine":13,"beginColumn":3,"endLine":13,"endColumn":4},"tokenRange":{"beginToken":{"kind":94,"text":"em"},"endToken":{"kind":94,"text":"em"}},"name":{"!":"com.github.javaparser.ast.expr.SimpleName","range":{"beginLine":13,"beginColumn":3,"endLine":13,"endColumn":4},"tokenRange":{"beginToken":{"kind":94,"text":"em"},"endToken":{"kind":94,"text":"em"}},"identifier":"em"}}}}},{"!":"com.github.javaparser.ast.stmt.ExpressionStmt","range":{"beginLine":16,"beginColumn":3,"endLine":16,"endColumn":30},"tokenRange":{"beginToken":{"kind":94,"text":"em"},"endToken":{"kind":103,"text":";"}},"expression":{"!":"com.github.javaparser.ast.expr.MethodCallExpr","range":{"beginLine":16,"beginColumn":3,"endLine":16,"endColumn":29},"tokenRange":{"beginToken":{"kind":94,"text":"em"},"endToken":{"kind":98,"text":")"}},"arguments":[],"name":{"!":"com.github.javaparser.ast.expr.SimpleName","range":{"beginLine":16,"beginColumn":23,"endLine":16,"endColumn":27},"tokenRange":{"beginToken":{"kind":94,"text":"begin"},"endToken":{"kind":94,"text":"begin"}},"identifier":"begin"},"scope":{"!":"com.github.javaparser.ast.expr.MethodCallExpr","range":{"beginLine":16,"beginColumn":3,"endLine":16,"endColumn":21},"tokenRange":{"beginToken":{"kind":94,"text":"em"},"endToken":{"kind":98,"text":")"}},"arguments":[],"name":{"!":"com.github.javaparser.ast.expr.SimpleName","range":{"beginLine":16,"beginColumn":6,"endLine":16,"endColumn":19},"tokenRange":{"beginToken":{"kind":94,"text":"getTransaction"},"endToken":{"kind":94,"text":"getTransaction"}},"identifier":"getTransaction"},"scope":{"!":"com.github.javaparser.ast.expr.NameExpr","range":{"beginLine":16,"beginColumn":3,"endLine":16,"endColumn":4},"tokenRange":{"beginToken":{"kind":94,"text":"em"},"endToken":{"kind":94,"text":"em"}},"name":{"!":"com.github.javaparser.ast.expr.SimpleName","range":{"beginLine":16,"beginColumn":3,"endLine":16,"endColumn":4},"tokenRange":{"beginToken":{"kind":94,"text":"em"},"endToken":{"kind":94,"text":"em"}},"identifier":"em"}}}},"comment":{"!":"com.github.javaparser.ast.comments.LineComment","range":{"beginLine":15,"beginColumn":3,"endLine":15,"endColumn":61},"tokenRange":{"beginToken":{"kind":5,"text":"// Revision (still 1) (ele1: removing non-existing element)"},"endToken":{"kind":5,"text":"// Revision (still 1) (ele1: removing non-existing element)"}},"content":" Revision (still 1) (ele1: removing non-existing element)"}},{"!":"com.github.javaparser.ast.stmt.ExpressionStmt","range":{"beginLine":17,"beginColumn":3,"endLine":17,"endColumn":62},"tokenRange":{"beginToken":{"kind":94,"text":"ele1"},"endToken":{"kind":103,"text":";"}},"expression":{"!":"com.github.javaparser.ast.expr.AssignExpr","range":{"beginLine":17,"beginColumn":3,"endLine":17,"endColumn":61},"tokenRange":{"beginToken":{"kind":94,"text":"ele1"},"endToken":{"kind":98,"text":")"}},"operator":"ASSIGN","target":{"!":"com.github.javaparser.ast.expr.NameExpr","range":{"beginLine":17,"beginColumn":3,"endLine":17,"endColumn":6},"tokenRange":{"beginToken":{"kind":94,"text":"ele1"},"endToken":{"kind":94,"text":"ele1"}},"name":{"!":"com.github.javaparser.ast.expr.SimpleName","range":{"beginLine":17,"beginColumn":3,"endLine":17,"endColumn":6},"tokenRange":{"beginToken":{"kind":94,"text":"ele1"},"endToken":{"kind":94,"text":"ele1"}},"identifier":"ele1"}},"value":{"!":"com.github.javaparser.ast.expr.MethodCallExpr","range":{"beginLine":17,"beginColumn":10,"endLine":17,"endColumn":61},"tokenRange":{"beginToken":{"kind":94,"text":"em"},"endToken":{"kind":98,"text":")"}},"arguments":[{"!":"com.github.javaparser.ast.expr.ClassExpr","range":{"beginLine":17,"beginColumn":19,"endLine":17,"endColumn":45},"tokenRange":{"beginToken":{"kind":94,"text":"EmbeddableListEntity1"},"endToken":{"kind":19,"text":"class"}},"type":{"!":"com.github.javaparser.ast.type.ClassOrInterfaceType","range":{"beginLine":17,"beginColumn":19,"endLine":17,"endColumn":39},"tokenRange":{"beginToken":{"kind":94,"text":"EmbeddableListEntity1"},"endToken":{"kind":94,"text":"EmbeddableListEntity1"}},"name":{"!":"com.github.javaparser.ast.expr.SimpleName","range":{"beginLine":17,"beginColumn":19,"endLine":17,"endColumn":39},"tokenRange":{"beginToken":{"kind":94,"text":"EmbeddableListEntity1"},"endToken":{"kind":94,"text":"EmbeddableListEntity1"}},"identifier":"EmbeddableListEntity1"},"annotations":[]}},{"!":"com.github.javaparser.ast.expr.MethodCallExpr","range":{"beginLine":17,"beginColumn":48,"endLine":17,"endColumn":59},"tokenRange":{"beginToken":{"kind":94,"text":"ele1"},"endToken":{"kind":98,"text":")"}},"arguments":[],"name":{"!":"com.github.javaparser.ast.expr.SimpleName","range":{"beginLine":17,"beginColumn":53,"endLine":17,"endColumn":57},"tokenRange":{"beginToken":{"kind":94,"text":"getId"},"endToken":{"kind":94,"text":"getId"}},"identifier":"getId"},"scope":{"!":"com.github.javaparser.ast.expr.NameExpr","range":{"beginLine":17,"beginColumn":48,"endLine":17,"endColumn":51},"tokenRange":{"beginToken":{"kind":94,"text":"ele1"},"endToken":{"kind":94,"text":"ele1"}},"name":{"!":"com.github.javaparser.ast.expr.SimpleName","range":{"beginLine":17,"beginColumn":48,"endLine":17,"endColumn":51},"tokenRange":{"beginToken":{"kind":94,"text":"ele1"},"endToken":{"kind":94,"text":"ele1"}},"identifier":"ele1"}}}],"name":{"!":"com.github.javaparser.ast.expr.SimpleName","range":{"beginLine":17,"beginColumn":13,"endLine":17,"endColumn":16},"tokenRange":{"beginToken":{"kind":94,"text":"find"},"endToken":{"kind":94,"text":"find"}},"identifier":"find"},"scope":{"!":"com.github.javaparser.ast.expr.NameExpr","range":{"beginLine":17,"beginColumn":10,"endLine":17,"endColumn":11},"tokenRange":{"beginToken":{"kind":94,"text":"em"},"endToken":{"kind":94,"text":"em"}},"name":{"!":"com.github.javaparser.ast.expr.SimpleName","range":{"beginLine":17,"beginColumn":10,"endLine":17,"endColumn":11},"tokenRange":{"beginToken":{"kind":94,"text":"em"},"endToken":{"kind":94,"text":"em"}},"identifier":"em"}}}}},{"!":"com.github.javaparser.ast.stmt.ExpressionStmt","range":{"beginLine":18,"beginColumn":3,"endLine":18,"endColumn":41},"tokenRange":{"beginToken":{"kind":94,"text":"ele1"},"endToken":{"kind":103,"text":";"}},"expression":{"!":"com.github.javaparser.ast.expr.MethodCallExpr","range":{"beginLine":18,"beginColumn":3,"endLine":18,"endColumn":40},"tokenRange":{"beginToken":{"kind":94,"text":"ele1"},"endToken":{"kind":98,"text":")"}},"arguments":[{"!":"com.github.javaparser.ast.expr.NameExpr","range":{"beginLine":18,"beginColumn":35,"endLine":18,"endColumn":38},"tokenRange":{"beginToken":{"kind":94,"text":"c3_2"},"endToken":{"kind":94,"text":"c3_2"}},"name":{"!":"com.github.javaparser.ast.expr.SimpleName","range":{"beginLine":18,"beginColumn":35,"endLine":18,"endColumn":38},"tokenRange":{"beginToken":{"kind":94,"text":"c3_2"},"endToken":{"kind":94,"text":"c3_2"}},"identifier":"c3_2"}}],"name":{"!":"com.github.javaparser.ast.expr.SimpleName","range":{"beginLine":18,"beginColumn":27,"endLine":18,"endColumn":32},"tokenRange":{"beginToken":{"kind":94,"text":"remove"},"endToken":{"kind":94,"text":"remove"}},"identifier":"remove"},"scope":{"!":"com.github.javaparser.ast.expr.MethodCallExpr","range":{"beginLine":18,"beginColumn":3,"endLine":18,"endColumn":25},"tokenRange":{"beginToken":{"kind":94,"text":"ele1"},"endToken":{"kind":98,"text":")"}},"arguments":[],"name":{"!":"com.github.javaparser.ast.expr.SimpleName","range":{"beginLine":18,"beginColumn":8,"endLine":18,"endColumn":23},"tokenRange":{"beginToken":{"kind":94,"text":"getComponentList"},"endToken":{"kind":94,"text":"getComponentList"}},"identifier":"getComponentList"},"scope":{"!":"com.github.javaparser.ast.expr.NameExpr","range":{"beginLine":18,"beginColumn":3,"endLine":18,"endColumn":6},"tokenRange":{"beginToken":{"kind":94,"text":"ele1"},"endToken":{"kind":94,"text":"ele1"}},"name":{"!":"com.github.javaparser.ast.expr.SimpleName","range":{"beginLine":18,"beginColumn":3,"endLine":18,"endColumn":6},"tokenRange":{"beginToken":{"kind":94,"text":"ele1"},"endToken":{"kind":94,"text":"ele1"}},"identifier":"ele1"}}}}},{"!":"com.github.javaparser.ast.stmt.ExpressionStmt","range":{"beginLine":19,"beginColumn":3,"endLine":19,"endColumn":31},"tokenRange":{"beginToken":{"kind":94,"text":"em"},"endToken":{"kind":103,"text":";"}},"expression":{"!":"com.github.javaparser.ast.expr.MethodCallExpr","range":{"beginLine":19,"beginColumn":3,"endLine":19,"endColumn":30},"tokenRange":{"beginToken":{"kind":94,"text":"em"},"endToken":{"kind":98,"text":")"}},"arguments":[],"name":{"!":"com.github.javaparser.ast.expr.SimpleName","range":{"beginLine":19,"beginColumn":23,"endLine":19,"endColumn":28},"tokenRange":{"beginToken":{"kind":94,"text":"commit"},"endToken":{"kind":94,"text":"commit"}},"identifier":"commit"},"scope":{"!":"com.github.javaparser.ast.expr.MethodCallExpr","range":{"beginLine":19,"beginColumn":3,"endLine":19,"endColumn":21},"tokenRange":{"beginToken":{"kind":94,"text":"em"},"endToken":{"kind":98,"text":")"}},"arguments":[],"name":{"!":"com.github.javaparser.ast.expr.SimpleName","range":{"beginLine":19,"beginColumn":6,"endLine":19,"endColumn":19},"tokenRange":{"beginToken":{"kind":94,"text":"getTransaction"},"endToken":{"kind":94,"text":"getTransaction"}},"identifier":"getTransaction"},"scope":{"!":"com.github.javaparser.ast.expr.NameExpr","range":{"beginLine":19,"beginColumn":3,"endLine":19,"endColumn":4},"tokenRange":{"beginToken":{"kind":94,"text":"em"},"endToken":{"kind":94,"text":"em"}},"name":{"!":"com.github.javaparser.ast.expr.SimpleName","range":{"beginLine":19,"beginColumn":3,"endLine":19,"endColumn":4},"tokenRange":{"beginToken":{"kind":94,"text":"em"},"endToken":{"kind":94,"text":"em"}},"identifier":"em"}}}}},{"!":"com.github.javaparser.ast.stmt.ExpressionStmt","range":{"beginLine":22,"beginColumn":3,"endLine":22,"endColumn":30},"tokenRange":{"beginToken":{"kind":94,"text":"em"},"endToken":{"kind":103,"text":";"}},"expression":{"!":"com.github.javaparser.ast.expr.MethodCallExpr","range":{"beginLine":22,"beginColumn":3,"endLine":22,"endColumn":29},"tokenRange":{"beginToken":{"kind":94,"text":"em"},"endToken":{"kind":98,"text":")"}},"arguments":[],"name":{"!":"com.github.javaparser.ast.expr.SimpleName","range":{"beginLine":22,"beginColumn":23,"endLine":22,"endColumn":27},"tokenRange":{"beginToken":{"kind":94,"text":"begin"},"endToken":{"kind":94,"text":"begin"}},"identifier":"begin"},"scope":{"!":"com.github.javaparser.ast.expr.MethodCallExpr","range":{"beginLine":22,"beginColumn":3,"endLine":22,"endColumn":21},"tokenRange":{"beginToken":{"kind":94,"text":"em"},"endToken":{"kind":98,"text":")"}},"arguments":[],"name":{"!":"com.github.javaparser.ast.expr.SimpleName","range":{"beginLine":22,"beginColumn":6,"endLine":22,"endColumn":19},"tokenRange":{"beginToken":{"kind":94,"text":"getTransaction"},"endToken":{"kind":94,"text":"getTransaction"}},"identifier":"getTransaction"},"scope":{"!":"com.github.javaparser.ast.expr.NameExpr","range":{"beginLine":22,"beginColumn":3,"endLine":22,"endColumn":4},"tokenRange":{"beginToken":{"kind":94,"text":"em"},"endToken":{"kind":94,"text":"em"}},"name":{"!":"com.github.javaparser.ast.expr.SimpleName","range":{"beginLine":22,"beginColumn":3,"endLine":22,"endColumn":4},"tokenRange":{"beginToken":{"kind":94,"text":"em"},"endToken":{"kind":94,"text":"em"}},"identifier":"em"}}}},"comment":{"!":"com.github.javaparser.ast.comments.LineComment","range":{"beginLine":21,"beginColumn":3,"endLine":21,"endColumn":42},"tokenRange":{"beginToken":{"kind":5,"text":"// Revision 2 (ele1: adding one element)"},"endToken":{"kind":5,"text":"// Revision 2 (ele1: adding one element)"}},"content":" Revision 2 (ele1: adding one element)"}},{"!":"com.github.javaparser.ast.stmt.ExpressionStmt","range":{"beginLine":23,"beginColumn":3,"endLine":23,"endColumn":62},"tokenRange":{"beginToken":{"kind":94,"text":"ele1"},"endToken":{"kind":103,"text":";"}},"expression":{"!":"com.github.javaparser.ast.expr.AssignExpr","range":{"beginLine":23,"beginColumn":3,"endLine":23,"endColumn":61},"tokenRange":{"beginToken":{"kind":94,"text":"ele1"},"endToken":{"kind":98,"text":")"}},"operator":"ASSIGN","target":{"!":"com.github.javaparser.ast.expr.NameExpr","range":{"beginLine":23,"beginColumn":3,"endLine":23,"endColumn":6},"tokenRange":{"beginToken":{"kind":94,"text":"ele1"},"endToken":{"kind":94,"text":"ele1"}},"name":{"!":"com.github.javaparser.ast.expr.SimpleName","range":{"beginLine":23,"beginColumn":3,"endLine":23,"endColumn":6},"tokenRange":{"beginToken":{"kind":94,"text":"ele1"},"endToken":{"kind":94,"text":"ele1"}},"identifier":"ele1"}},"value":{"!":"com.github.javaparser.ast.expr.MethodCallExpr","range":{"beginLine":23,"beginColumn":10,"endLine":23,"endColumn":61},"tokenRange":{"beginToken":{"kind":94,"text":"em"},"endToken":{"kind":98,"text":")"}},"arguments":[{"!":"com.github.javaparser.ast.expr.ClassExpr","range":{"beginLine":23,"beginColumn":19,"endLine":23,"endColumn":45},"tokenRange":{"beginToken":{"kind":94,"text":"EmbeddableListEntity1"},"endToken":{"kind":19,"text":"class"}},"type":{"!":"com.github.javaparser.ast.type.ClassOrInterfaceType","range":{"beginLine":23,"beginColumn":19,"endLine":23,"endColumn":39},"tokenRange":{"beginToken":{"kind":94,"text":"EmbeddableListEntity1"},"endToken":{"kind":94,"text":"EmbeddableListEntity1"}},"name":{"!":"com.github.javaparser.ast.expr.SimpleName","range":{"beginLine":23,"beginColumn":19,"endLine":23,"endColumn":39},"tokenRange":{"beginToken":{"kind":94,"text":"EmbeddableListEntity1"},"endToken":{"kind":94,"text":"EmbeddableListEntity1"}},"identifier":"EmbeddableListEntity1"},"annotations":[]}},{"!":"com.github.javaparser.ast.expr.MethodCallExpr","range":{"beginLine":23,"beginColumn":48,"endLine":23,"endColumn":59},"tokenRange":{"beginToken":{"kind":94,"text":"ele1"},"endToken":{"kind":98,"text":")"}},"arguments":[],"name":{"!":"com.github.javaparser.ast.expr.SimpleName","range":{"beginLine":23,"beginColumn":53,"endLine":23,"endColumn":57},"tokenRange":{"beginToken":{"kind":94,"text":"getId"},"endToken":{"kind":94,"text":"getId"}},"identifier":"getId"},"scope":{"!":"com.github.javaparser.ast.expr.NameExpr","range":{"beginLine":23,"beginColumn":48,"endLine":23,"endColumn":51},"tokenRange":{"beginToken":{"kind":94,"text":"ele1"},"endToken":{"kind":94,"text":"ele1"}},"name":{"!":"com.github.javaparser.ast.expr.SimpleName","range":{"beginLine":23,"beginColumn":48,"endLine":23,"endColumn":51},"tokenRange":{"beginToken":{"kind":94,"text":"ele1"},"endToken":{"kind":94,"text":"ele1"}},"identifier":"ele1"}}}],"name":{"!":"com.github.javaparser.ast.expr.SimpleName","range":{"beginLine":23,"beginColumn":13,"endLine":23,"endColumn":16},"tokenRange":{"beginToken":{"kind":94,"text":"find"},"endToken":{"kind":94,"text":"find"}},"identifier":"find"},"scope":{"!":"com.github.javaparser.ast.expr.NameExpr","range":{"beginLine":23,"beginColumn":10,"endLine":23,"endColumn":11},"tokenRange":{"beginToken":{"kind":94,"text":"em"},"endToken":{"kind":94,"text":"em"}},"name":{"!":"com.github.javaparser.ast.expr.SimpleName","range":{"beginLine":23,"beginColumn":10,"endLine":23,"endColumn":11},"tokenRange":{"beginToken":{"kind":94,"text":"em"},"endToken":{"kind":94,"text":"em"}},"identifier":"em"}}}}},{"!":"com.github.javaparser.ast.stmt.ExpressionStmt","range":{"beginLine":24,"beginColumn":3,"endLine":24,"endColumn":38},"tokenRange":{"beginToken":{"kind":94,"text":"ele1"},"endToken":{"kind":103,"text":";"}},"expression":{"!":"com.github.javaparser.ast.expr.MethodCallExpr","range":{"beginLine":24,"beginColumn":3,"endLine":24,"endColumn":37},"tokenRange":{"beginToken":{"kind":94,"text":"ele1"},"endToken":{"kind":98,"text":")"}},"arguments":[{"!":"com.github.javaparser.ast.expr.NameExpr","range":{"beginLine":24,"beginColumn":32,"endLine":24,"endColumn":35},"tokenRange":{"beginToken":{"kind":94,"text":"c3_2"},"endToken":{"kind":94,"text":"c3_2"}},"name":{"!":"com.github.javaparser.ast.expr.SimpleName","range":{"beginLine":24,"beginColumn":32,"endLine":24,"endColumn":35},"tokenRange":{"beginToken":{"kind":94,"text":"c3_2"},"endToken":{"kind":94,"text":"c3_2"}},"identifier":"c3_2"}}],"name":{"!":"com.github.javaparser.ast.expr.SimpleName","range":{"beginLine":24,"beginColumn":27,"endLine":24,"endColumn":29},"tokenRange":{"beginToken":{"kind":94,"text":"add"},"endToken":{"kind":94,"text":"add"}},"identifier":"add"},"scope":{"!":"com.github.javaparser.ast.expr.MethodCallExpr","range":{"beginLine":24,"beginColumn":3,"endLine":24,"endColumn":25},"tokenRange":{"beginToken":{"kind":94,"text":"ele1"},"endToken":{"kind":98,"text":")"}},"arguments":[],"name":{"!":"com.github.javaparser.ast.expr.SimpleName","range":{"beginLine":24,"beginColumn":8,"endLine":24,"endColumn":23},"tokenRange":{"beginToken":{"kind":94,"text":"getComponentList"},"endToken":{"kind":94,"text":"getComponentList"}},"identifier":"getComponentList"},"scope":{"!":"com.github.javaparser.ast.expr.NameExpr","range":{"beginLine":24,"beginColumn":3,"endLine":24,"endColumn":6},"tokenRange":{"beginToken":{"kind":94,"text":"ele1"},"endToken":{"kind":94,"text":"ele1"}},"name":{"!":"com.github.javaparser.ast.expr.SimpleName","range":{"beginLine":24,"beginColumn":3,"endLine":24,"endColumn":6},"tokenRange":{"beginToken":{"kind":94,"text":"ele1"},"endToken":{"kind":94,"text":"ele1"}},"identifier":"ele1"}}}}},{"!":"com.github.javaparser.ast.stmt.ExpressionStmt","range":{"beginLine":25,"beginColumn":3,"endLine":25,"endColumn":31},"tokenRange":{"beginToken":{"kind":94,"text":"em"},"endToken":{"kind":103,"text":";"}},"expression":{"!":"com.github.javaparser.ast.expr.MethodCallExpr","range":{"beginLine":25,"beginColumn":3,"endLine":25,"endColumn":30},"tokenRange":{"beginToken":{"kind":94,"text":"em"},"endToken":{"kind":98,"text":")"}},"arguments":[],"name":{"!":"com.github.javaparser.ast.expr.SimpleName","range":{"beginLine":25,"beginColumn":23,"endLine":25,"endColumn":28},"tokenRange":{"beginToken":{"kind":94,"text":"commit"},"endToken":{"kind":94,"text":"commit"}},"identifier":"commit"},"scope":{"!":"com.github.javaparser.ast.expr.MethodCallExpr","range":{"beginLine":25,"beginColumn":3,"endLine":25,"endColumn":21},"tokenRange":{"beginToken":{"kind":94,"text":"em"},"endToken":{"kind":98,"text":")"}},"arguments":[],"name":{"!":"com.github.javaparser.ast.expr.SimpleName","range":{"beginLine":25,"beginColumn":6,"endLine":25,"endColumn":19},"tokenRange":{"beginToken":{"kind":94,"text":"getTransaction"},"endToken":{"kind":94,"text":"getTransaction"}},"identifier":"getTransaction"},"scope":{"!":"com.github.javaparser.ast.expr.NameExpr","range":{"beginLine":25,"beginColumn":3,"endLine":25,"endColumn":4},"tokenRange":{"beginToken":{"kind":94,"text":"em"},"endToken":{"kind":94,"text":"em"}},"name":{"!":"com.github.javaparser.ast.expr.SimpleName","range":{"beginLine":25,"beginColumn":3,"endLine":25,"endColumn":4},"tokenRange":{"beginToken":{"kind":94,"text":"em"},"endToken":{"kind":94,"text":"em"}},"identifier":"em"}}}}},{"!":"com.github.javaparser.ast.stmt.ExpressionStmt","range":{"beginLine":28,"beginColumn":3,"endLine":28,"endColumn":30},"tokenRange":{"beginToken":{"kind":94,"text":"em"},"endToken":{"kind":103,"text":";"}},"expression":{"!":"com.github.javaparser.ast.expr.MethodCallExpr","range":{"beginLine":28,"beginColumn":3,"endLine":28,"endColumn":29},"tokenRange":{"beginToken":{"kind":94,"text":"em"},"endToken":{"kind":98,"text":")"}},"arguments":[],"name":{"!":"com.github.javaparser.ast.expr.SimpleName","range":{"beginLine":28,"beginColumn":23,"endLine":28,"endColumn":27},"tokenRange":{"beginToken":{"kind":94,"text":"begin"},"endToken":{"kind":94,"text":"begin"}},"identifier":"begin"},"scope":{"!":"com.github.javaparser.ast.expr.MethodCallExpr","range":{"beginLine":28,"beginColumn":3,"endLine":28,"endColumn":21},"tokenRange":{"beginToken":{"kind":94,"text":"em"},"endToken":{"kind":98,"text":")"}},"arguments":[],"name":{"!":"com.github.javaparser.ast.expr.SimpleName","range":{"beginLine":28,"beginColumn":6,"endLine":28,"endColumn":19},"tokenRange":{"beginToken":{"kind":94,"text":"getTransaction"},"endToken":{"kind":94,"text":"getTransaction"}},"identifier":"getTransaction"},"scope":{"!":"com.github.javaparser.ast.expr.NameExpr","range":{"beginLine":28,"beginColumn":3,"endLine":28,"endColumn":4},"tokenRange":{"beginToken":{"kind":94,"text":"em"},"endToken":{"kind":94,"text":"em"}},"name":{"!":"com.github.javaparser.ast.expr.SimpleName","range":{"beginLine":28,"beginColumn":3,"endLine":28,"endColumn":4},"tokenRange":{"beginToken":{"kind":94,"text":"em"},"endToken":{"kind":94,"text":"em"}},"identifier":"em"}}}},"comment":{"!":"com.github.javaparser.ast.comments.LineComment","range":{"beginLine":27,"beginColumn":3,"endLine":27,"endColumn":51},"tokenRange":{"beginToken":{"kind":5,"text":"// Revision 3 (ele1: adding one existing element)"},"endToken":{"kind":5,"text":"// Revision 3 (ele1: adding one existing element)"}},"content":" Revision 3 (ele1: adding one existing element)"}},{"!":"com.github.javaparser.ast.stmt.ExpressionStmt","range":{"beginLine":29,"beginColumn":3,"endLine":29,"endColumn":62},"tokenRange":{"beginToken":{"kind":94,"text":"ele1"},"endToken":{"kind":103,"text":";"}},"expression":{"!":"com.github.javaparser.ast.expr.AssignExpr","range":{"beginLine":29,"beginColumn":3,"endLine":29,"endColumn":61},"tokenRange":{"beginToken":{"kind":94,"text":"ele1"},"endToken":{"kind":98,"text":")"}},"operator":"ASSIGN","target":{"!":"com.github.javaparser.ast.expr.NameExpr","range":{"beginLine":29,"beginColumn":3,"endLine":29,"endColumn":6},"tokenRange":{"beginToken":{"kind":94,"text":"ele1"},"endToken":{"kind":94,"text":"ele1"}},"name":{"!":"com.github.javaparser.ast.expr.SimpleName","range":{"beginLine":29,"beginColumn":3,"endLine":29,"endColumn":6},"tokenRange":{"beginToken":{"kind":94,"text":"ele1"},"endToken":{"kind":94,"text":"ele1"}},"identifier":"ele1"}},"value":{"!":"com.github.javaparser.ast.expr.MethodCallExpr","range":{"beginLine":29,"beginColumn":10,"endLine":29,"endColumn":61},"tokenRange":{"beginToken":{"kind":94,"text":"em"},"endToken":{"kind":98,"text":")"}},"arguments":[{"!":"com.github.javaparser.ast.expr.ClassExpr","range":{"beginLine":29,"beginColumn":19,"endLine":29,"endColumn":45},"tokenRange":{"beginToken":{"kind":94,"text":"EmbeddableListEntity1"},"endToken":{"kind":19,"text":"class"}},"type":{"!":"com.github.javaparser.ast.type.ClassOrInterfaceType","range":{"beginLine":29,"beginColumn":19,"endLine":29,"endColumn":39},"tokenRange":{"beginToken":{"kind":94,"text":"EmbeddableListEntity1"},"endToken":{"kind":94,"text":"EmbeddableListEntity1"}},"name":{"!":"com.github.javaparser.ast.expr.SimpleName","range":{"beginLine":29,"beginColumn":19,"endLine":29,"endColumn":39},"tokenRange":{"beginToken":{"kind":94,"text":"EmbeddableListEntity1"},"endToken":{"kind":94,"text":"EmbeddableListEntity1"}},"identifier":"EmbeddableListEntity1"},"annotations":[]}},{"!":"com.github.javaparser.ast.expr.MethodCallExpr","range":{"beginLine":29,"beginColumn":48,"endLine":29,"endColumn":59},"tokenRange":{"beginToken":{"kind":94,"text":"ele1"},"endToken":{"kind":98,"text":")"}},"arguments":[],"name":{"!":"com.github.javaparser.ast.expr.SimpleName","range":{"beginLine":29,"beginColumn":53,"endLine":29,"endColumn":57},"tokenRange":{"beginToken":{"kind":94,"text":"getId"},"endToken":{"kind":94,"text":"getId"}},"identifier":"getId"},"scope":{"!":"com.github.javaparser.ast.expr.NameExpr","range":{"beginLine":29,"beginColumn":48,"endLine":29,"endColumn":51},"tokenRange":{"beginToken":{"kind":94,"text":"ele1"},"endToken":{"kind":94,"text":"ele1"}},"name":{"!":"com.github.javaparser.ast.expr.SimpleName","range":{"beginLine":29,"beginColumn":48,"endLine":29,"endColumn":51},"tokenRange":{"beginToken":{"kind":94,"text":"ele1"},"endToken":{"kind":94,"text":"ele1"}},"identifier":"ele1"}}}],"name":{"!":"com.github.javaparser.ast.expr.SimpleName","range":{"beginLine":29,"beginColumn":13,"endLine":29,"endColumn":16},"tokenRange":{"beginToken":{"kind":94,"text":"find"},"endToken":{"kind":94,"text":"find"}},"identifier":"find"},"scope":{"!":"com.github.javaparser.ast.expr.NameExpr","range":{"beginLine":29,"beginColumn":10,"endLine":29,"endColumn":11},"tokenRange":{"beginToken":{"kind":94,"text":"em"},"endToken":{"kind":94,"text":"em"}},"name":{"!":"com.github.javaparser.ast.expr.SimpleName","range":{"beginLine":29,"beginColumn":10,"endLine":29,"endColumn":11},"tokenRange":{"beginToken":{"kind":94,"text":"em"},"endToken":{"kind":94,"text":"em"}},"identifier":"em"}}}}},{"!":"com.github.javaparser.ast.stmt.ExpressionStmt","range":{"beginLine":30,"beginColumn":3,"endLine":30,"endColumn":38},"tokenRange":{"beginToken":{"kind":94,"text":"ele1"},"endToken":{"kind":103,"text":";"}},"expression":{"!":"com.github.javaparser.ast.expr.MethodCallExpr","range":{"beginLine":30,"beginColumn":3,"endLine":30,"endColumn":37},"tokenRange":{"beginToken":{"kind":94,"text":"ele1"},"endToken":{"kind":98,"text":")"}},"arguments":[{"!":"com.github.javaparser.ast.expr.NameExpr","range":{"beginLine":30,"beginColumn":32,"endLine":30,"endColumn":35},"tokenRange":{"beginToken":{"kind":94,"text":"c3_1"},"endToken":{"kind":94,"text":"c3_1"}},"name":{"!":"com.github.javaparser.ast.expr.SimpleName","range":{"beginLine":30,"beginColumn":32,"endLine":30,"endColumn":35},"tokenRange":{"beginToken":{"kind":94,"text":"c3_1"},"endToken":{"kind":94,"text":"c3_1"}},"identifier":"c3_1"}}],"name":{"!":"com.github.javaparser.ast.expr.SimpleName","range":{"beginLine":30,"beginColumn":27,"endLine":30,"endColumn":29},"tokenRange":{"beginToken":{"kind":94,"text":"add"},"endToken":{"kind":94,"text":"add"}},"identifier":"add"},"scope":{"!":"com.github.javaparser.ast.expr.MethodCallExpr","range":{"beginLine":30,"beginColumn":3,"endLine":30,"endColumn":25},"tokenRange":{"beginToken":{"kind":94,"text":"ele1"},"endToken":{"kind":98,"text":")"}},"arguments":[],"name":{"!":"com.github.javaparser.ast.expr.SimpleName","range":{"beginLine":30,"beginColumn":8,"endLine":30,"endColumn":23},"tokenRange":{"beginToken":{"kind":94,"text":"getComponentList"},"endToken":{"kind":94,"text":"getComponentList"}},"identifier":"getComponentList"},"scope":{"!":"com.github.javaparser.ast.expr.NameExpr","range":{"beginLine":30,"beginColumn":3,"endLine":30,"endColumn":6},"tokenRange":{"beginToken":{"kind":94,"text":"ele1"},"endToken":{"kind":94,"text":"ele1"}},"name":{"!":"com.github.javaparser.ast.expr.SimpleName","range":{"beginLine":30,"beginColumn":3,"endLine":30,"endColumn":6},"tokenRange":{"beginToken":{"kind":94,"text":"ele1"},"endToken":{"kind":94,"text":"ele1"}},"identifier":"ele1"}}}}},{"!":"com.github.javaparser.ast.stmt.ExpressionStmt","range":{"beginLine":31,"beginColumn":3,"endLine":31,"endColumn":31},"tokenRange":{"beginToken":{"kind":94,"text":"em"},"endToken":{"kind":103,"text":";"}},"expression":{"!":"com.github.javaparser.ast.expr.MethodCallExpr","range":{"beginLine":31,"beginColumn":3,"endLine":31,"endColumn":30},"tokenRange":{"beginToken":{"kind":94,"text":"em"},"endToken":{"kind":98,"text":")"}},"arguments":[],"name":{"!":"com.github.javaparser.ast.expr.SimpleName","range":{"beginLine":31,"beginColumn":23,"endLine":31,"endColumn":28},"tokenRange":{"beginToken":{"kind":94,"text":"commit"},"endToken":{"kind":94,"text":"commit"}},"identifier":"commit"},"scope":{"!":"com.github.javaparser.ast.expr.MethodCallExpr","range":{"beginLine":31,"beginColumn":3,"endLine":31,"endColumn":21},"tokenRange":{"beginToken":{"kind":94,"text":"em"},"endToken":{"kind":98,"text":")"}},"arguments":[],"name":{"!":"com.github.javaparser.ast.expr.SimpleName","range":{"beginLine":31,"beginColumn":6,"endLine":31,"endColumn":19},"tokenRange":{"beginToken":{"kind":94,"text":"getTransaction"},"endToken":{"kind":94,"text":"getTransaction"}},"identifier":"getTransaction"},"scope":{"!":"com.github.javaparser.ast.expr.NameExpr","range":{"beginLine":31,"beginColumn":3,"endLine":31,"endColumn":4},"tokenRange":{"beginToken":{"kind":94,"text":"em"},"endToken":{"kind":94,"text":"em"}},"name":{"!":"com.github.javaparser.ast.expr.SimpleName","range":{"beginLine":31,"beginColumn":3,"endLine":31,"endColumn":4},"tokenRange":{"beginToken":{"kind":94,"text":"em"},"endToken":{"kind":94,"text":"em"}},"identifier":"em"}}}}},{"!":"com.github.javaparser.ast.stmt.ExpressionStmt","range":{"beginLine":34,"beginColumn":3,"endLine":34,"endColumn":30},"tokenRange":{"beginToken":{"kind":94,"text":"em"},"endToken":{"kind":103,"text":";"}},"expression":{"!":"com.github.javaparser.ast.expr.MethodCallExpr","range":{"beginLine":34,"beginColumn":3,"endLine":34,"endColumn":29},"tokenRange":{"beginToken":{"kind":94,"text":"em"},"endToken":{"kind":98,"text":")"}},"arguments":[],"name":{"!":"com.github.javaparser.ast.expr.SimpleName","range":{"beginLine":34,"beginColumn":23,"endLine":34,"endColumn":27},"tokenRange":{"beginToken":{"kind":94,"text":"begin"},"endToken":{"kind":94,"text":"begin"}},"identifier":"begin"},"scope":{"!":"com.github.javaparser.ast.expr.MethodCallExpr","range":{"beginLine":34,"beginColumn":3,"endLine":34,"endColumn":21},"tokenRange":{"beginToken":{"kind":94,"text":"em"},"endToken":{"kind":98,"text":")"}},"arguments":[],"name":{"!":"com.github.javaparser.ast.expr.SimpleName","range":{"beginLine":34,"beginColumn":6,"endLine":34,"endColumn":19},"tokenRange":{"beginToken":{"kind":94,"text":"getTransaction"},"endToken":{"kind":94,"text":"getTransaction"}},"identifier":"getTransaction"},"scope":{"!":"com.github.javaparser.ast.expr.NameExpr","range":{"beginLine":34,"beginColumn":3,"endLine":34,"endColumn":4},"tokenRange":{"beginToken":{"kind":94,"text":"em"},"endToken":{"kind":94,"text":"em"}},"name":{"!":"com.github.javaparser.ast.expr.SimpleName","range":{"beginLine":34,"beginColumn":3,"endLine":34,"endColumn":4},"tokenRange":{"beginToken":{"kind":94,"text":"em"},"endToken":{"kind":94,"text":"em"}},"identifier":"em"}}}},"comment":{"!":"com.github.javaparser.ast.comments.LineComment","range":{"beginLine":33,"beginColumn":3,"endLine":33,"endColumn":53},"tokenRange":{"beginToken":{"kind":5,"text":"// Revision 4 (ele1: removing one existing element)"},"endToken":{"kind":5,"text":"// Revision 4 (ele1: removing one existing element)"}},"content":" Revision 4 (ele1: removing one existing element)"}},{"!":"com.github.javaparser.ast.stmt.ExpressionStmt","range":{"beginLine":35,"beginColumn":3,"endLine":35,"endColumn":62},"tokenRange":{"beginToken":{"kind":94,"text":"ele1"},"endToken":{"kind":103,"text":";"}},"expression":{"!":"com.github.javaparser.ast.expr.AssignExpr","range":{"beginLine":35,"beginColumn":3,"endLine":35,"endColumn":61},"tokenRange":{"beginToken":{"kind":94,"text":"ele1"},"endToken":{"kind":98,"text":")"}},"operator":"ASSIGN","target":{"!":"com.github.javaparser.ast.expr.NameExpr","range":{"beginLine":35,"beginColumn":3,"endLine":35,"endColumn":6},"tokenRange":{"beginToken":{"kind":94,"text":"ele1"},"endToken":{"kind":94,"text":"ele1"}},"name":{"!":"com.github.javaparser.ast.expr.SimpleName","range":{"beginLine":35,"beginColumn":3,"endLine":35,"endColumn":6},"tokenRange":{"beginToken":{"kind":94,"text":"ele1"},"endToken":{"kind":94,"text":"ele1"}},"identifier":"ele1"}},"value":{"!":"com.github.javaparser.ast.expr.MethodCallExpr","range":{"beginLine":35,"beginColumn":10,"endLine":35,"endColumn":61},"tokenRange":{"beginToken":{"kind":94,"text":"em"},"endToken":{"kind":98,"text":")"}},"arguments":[{"!":"com.github.javaparser.ast.expr.ClassExpr","range":{"beginLine":35,"beginColumn":19,"endLine":35,"endColumn":45},"tokenRange":{"beginToken":{"kind":94,"text":"EmbeddableListEntity1"},"endToken":{"kind":19,"text":"class"}},"type":{"!":"com.github.javaparser.ast.type.ClassOrInterfaceType","range":{"beginLine":35,"beginColumn":19,"endLine":35,"endColumn":39},"tokenRange":{"beginToken":{"kind":94,"text":"EmbeddableListEntity1"},"endToken":{"kind":94,"text":"EmbeddableListEntity1"}},"name":{"!":"com.github.javaparser.ast.expr.SimpleName","range":{"beginLine":35,"beginColumn":19,"endLine":35,"endColumn":39},"tokenRange":{"beginToken":{"kind":94,"text":"EmbeddableListEntity1"},"endToken":{"kind":94,"text":"EmbeddableListEntity1"}},"identifier":"EmbeddableListEntity1"},"annotations":[]}},{"!":"com.github.javaparser.ast.expr.MethodCallExpr","range":{"beginLine":35,"beginColumn":48,"endLine":35,"endColumn":59},"tokenRange":{"beginToken":{"kind":94,"text":"ele1"},"endToken":{"kind":98,"text":")"}},"arguments":[],"name":{"!":"com.github.javaparser.ast.expr.SimpleName","range":{"beginLine":35,"beginColumn":53,"endLine":35,"endColumn":57},"tokenRange":{"beginToken":{"kind":94,"text":"getId"},"endToken":{"kind":94,"text":"getId"}},"identifier":"getId"},"scope":{"!":"com.github.javaparser.ast.expr.NameExpr","range":{"beginLine":35,"beginColumn":48,"endLine":35,"endColumn":51},"tokenRange":{"beginToken":{"kind":94,"text":"ele1"},"endToken":{"kind":94,"text":"ele1"}},"name":{"!":"com.github.javaparser.ast.expr.SimpleName","range":{"beginLine":35,"beginColumn":48,"endLine":35,"endColumn":51},"tokenRange":{"beginToken":{"kind":94,"text":"ele1"},"endToken":{"kind":94,"text":"ele1"}},"identifier":"ele1"}}}],"name":{"!":"com.github.javaparser.ast.expr.SimpleName","range":{"beginLine":35,"beginColumn":13,"endLine":35,"endColumn":16},"tokenRange":{"beginToken":{"kind":94,"text":"find"},"endToken":{"kind":94,"text":"find"}},"identifier":"find"},"scope":{"!":"com.github.javaparser.ast.expr.NameExpr","range":{"beginLine":35,"beginColumn":10,"endLine":35,"endColumn":11},"tokenRange":{"beginToken":{"kind":94,"text":"em"},"endToken":{"kind":94,"text":"em"}},"name":{"!":"com.github.javaparser.ast.expr.SimpleName","range":{"beginLine":35,"beginColumn":10,"endLine":35,"endColumn":11},"tokenRange":{"beginToken":{"kind":94,"text":"em"},"endToken":{"kind":94,"text":"em"}},"identifier":"em"}}}}},{"!":"com.github.javaparser.ast.stmt.ExpressionStmt","range":{"beginLine":36,"beginColumn":3,"endLine":36,"endColumn":41},"tokenRange":{"beginToken":{"kind":94,"text":"ele1"},"endToken":{"kind":103,"text":";"}},"expression":{"!":"com.github.javaparser.ast.expr.MethodCallExpr","range":{"beginLine":36,"beginColumn":3,"endLine":36,"endColumn":40},"tokenRange":{"beginToken":{"kind":94,"text":"ele1"},"endToken":{"kind":98,"text":")"}},"arguments":[{"!":"com.github.javaparser.ast.expr.NameExpr","range":{"beginLine":36,"beginColumn":35,"endLine":36,"endColumn":38},"tokenRange":{"beginToken":{"kind":94,"text":"c3_2"},"endToken":{"kind":94,"text":"c3_2"}},"name":{"!":"com.github.javaparser.ast.expr.SimpleName","range":{"beginLine":36,"beginColumn":35,"endLine":36,"endColumn":38},"tokenRange":{"beginToken":{"kind":94,"text":"c3_2"},"endToken":{"kind":94,"text":"c3_2"}},"identifier":"c3_2"}}],"name":{"!":"com.github.javaparser.ast.expr.SimpleName","range":{"beginLine":36,"beginColumn":27,"endLine":36,"endColumn":32},"tokenRange":{"beginToken":{"kind":94,"text":"remove"},"endToken":{"kind":94,"text":"remove"}},"identifier":"remove"},"scope":{"!":"com.github.javaparser.ast.expr.MethodCallExpr","range":{"beginLine":36,"beginColumn":3,"endLine":36,"endColumn":25},"tokenRange":{"beginToken":{"kind":94,"text":"ele1"},"endToken":{"kind":98,"text":")"}},"arguments":[],"name":{"!":"com.github.javaparser.ast.expr.SimpleName","range":{"beginLine":36,"beginColumn":8,"endLine":36,"endColumn":23},"tokenRange":{"beginToken":{"kind":94,"text":"getComponentList"},"endToken":{"kind":94,"text":"getComponentList"}},"identifier":"getComponentList"},"scope":{"!":"com.github.javaparser.ast.expr.NameExpr","range":{"beginLine":36,"beginColumn":3,"endLine":36,"endColumn":6},"tokenRange":{"beginToken":{"kind":94,"text":"ele1"},"endToken":{"kind":94,"text":"ele1"}},"name":{"!":"com.github.javaparser.ast.expr.SimpleName","range":{"beginLine":36,"beginColumn":3,"endLine":36,"endColumn":6},"tokenRange":{"beginToken":{"kind":94,"text":"ele1"},"endToken":{"kind":94,"text":"ele1"}},"identifier":"ele1"}}}}},{"!":"com.github.javaparser.ast.stmt.ExpressionStmt","range":{"beginLine":37,"beginColumn":3,"endLine":37,"endColumn":31},"tokenRange":{"beginToken":{"kind":94,"text":"em"},"endToken":{"kind":103,"text":";"}},"expression":{"!":"com.github.javaparser.ast.expr.MethodCallExpr","range":{"beginLine":37,"beginColumn":3,"endLine":37,"endColumn":30},"tokenRange":{"beginToken":{"kind":94,"text":"em"},"endToken":{"kind":98,"text":")"}},"arguments":[],"name":{"!":"com.github.javaparser.ast.expr.SimpleName","range":{"beginLine":37,"beginColumn":23,"endLine":37,"endColumn":28},"tokenRange":{"beginToken":{"kind":94,"text":"commit"},"endToken":{"kind":94,"text":"commit"}},"identifier":"commit"},"scope":{"!":"com.github.javaparser.ast.expr.MethodCallExpr","range":{"beginLine":37,"beginColumn":3,"endLine":37,"endColumn":21},"tokenRange":{"beginToken":{"kind":94,"text":"em"},"endToken":{"kind":98,"text":")"}},"arguments":[],"name":{"!":"com.github.javaparser.ast.expr.SimpleName","range":{"beginLine":37,"beginColumn":6,"endLine":37,"endColumn":19},"tokenRange":{"beginToken":{"kind":94,"text":"getTransaction"},"endToken":{"kind":94,"text":"getTransaction"}},"identifier":"getTransaction"},"scope":{"!":"com.github.javaparser.ast.expr.NameExpr","range":{"beginLine":37,"beginColumn":3,"endLine":37,"endColumn":4},"tokenRange":{"beginToken":{"kind":94,"text":"em"},"endToken":{"kind":94,"text":"em"}},"name":{"!":"com.github.javaparser.ast.expr.SimpleName","range":{"beginLine":37,"beginColumn":3,"endLine":37,"endColumn":4},"tokenRange":{"beginToken":{"kind":94,"text":"em"},"endToken":{"kind":94,"text":"em"}},"identifier":"em"}}}}},{"!":"com.github.javaparser.ast.stmt.ExpressionStmt","range":{"beginLine":39,"beginColumn":3,"endLine":39,"endColumn":25},"tokenRange":{"beginToken":{"kind":94,"text":"ele1_id"},"endToken":{"kind":103,"text":";"}},"expression":{"!":"com.github.javaparser.ast.expr.AssignExpr","range":{"beginLine":39,"beginColumn":3,"endLine":39,"endColumn":24},"tokenRange":{"beginToken":{"kind":94,"text":"ele1_id"},"endToken":{"kind":98,"text":")"}},"operator":"ASSIGN","target":{"!":"com.github.javaparser.ast.expr.NameExpr","range":{"beginLine":39,"beginColumn":3,"endLine":39,"endColumn":9},"tokenRange":{"beginToken":{"kind":94,"text":"ele1_id"},"endToken":{"kind":94,"text":"ele1_id"}},"name":{"!":"com.github.javaparser.ast.expr.SimpleName","range":{"beginLine":39,"beginColumn":3,"endLine":39,"endColumn":9},"tokenRange":{"beginToken":{"kind":94,"text":"ele1_id"},"endToken":{"kind":94,"text":"ele1_id"}},"identifier":"ele1_id"}},"value":{"!":"com.github.javaparser.ast.expr.MethodCallExpr","range":{"beginLine":39,"beginColumn":13,"endLine":39,"endColumn":24},"tokenRange":{"beginToken":{"kind":94,"text":"ele1"},"endToken":{"kind":98,"text":")"}},"arguments":[],"name":{"!":"com.github.javaparser.ast.expr.SimpleName","range":{"beginLine":39,"beginColumn":18,"endLine":39,"endColumn":22},"tokenRange":{"beginToken":{"kind":94,"text":"getId"},"endToken":{"kind":94,"text":"getId"}},"identifier":"getId"},"scope":{"!":"com.github.javaparser.ast.expr.NameExpr","range":{"beginLine":39,"beginColumn":13,"endLine":39,"endColumn":16},"tokenRange":{"beginToken":{"kind":94,"text":"ele1"},"endToken":{"kind":94,"text":"ele1"}},"name":{"!":"com.github.javaparser.ast.expr.SimpleName","range":{"beginLine":39,"beginColumn":13,"endLine":39,"endColumn":16},"tokenRange":{"beginToken":{"kind":94,"text":"ele1"},"endToken":{"kind":94,"text":"ele1"}},"identifier":"ele1"}}}}},{"!":"com.github.javaparser.ast.stmt.ExpressionStmt","range":{"beginLine":41,"beginColumn":3,"endLine":41,"endColumn":13},"tokenRange":{"beginToken":{"kind":94,"text":"em"},"endToken":{"kind":103,"text":";"}},"expression":{"!":"com.github.javaparser.ast.expr.MethodCallExpr","range":{"beginLine":41,"beginColumn":3,"endLine":41,"endColumn":12},"tokenRange":{"beginToken":{"kind":94,"text":"em"},"endToken":{"kind":98,"text":")"}},"arguments":[],"name":{"!":"com.github.javaparser.ast.expr.SimpleName","range":{"beginLine":41,"beginColumn":6,"endLine":41,"endColumn":10},"tokenRange":{"beginToken":{"kind":94,"text":"close"},"endToken":{"kind":94,"text":"close"}},"identifier":"close"},"scope":{"!":"com.github.javaparser.ast.expr.NameExpr","range":{"beginLine":41,"beginColumn":3,"endLine":41,"endColumn":4},"tokenRange":{"beginToken":{"kind":94,"text":"em"},"endToken":{"kind":94,"text":"em"}},"name":{"!":"com.github.javaparser.ast.expr.SimpleName","range":{"beginLine":41,"beginColumn":3,"endLine":41,"endColumn":4},"tokenRange":{"beginToken":{"kind":94,"text":"em"},"endToken":{"kind":94,"text":"em"}},"identifier":"em"}}}}]},"type":{"!":"com.github.javaparser.ast.type.VoidType","range":{"beginLine":4,"beginColumn":9,"endLine":4,"endColumn":12},"tokenRange":{"beginToken":{"kind":62,"text":"void"},"endToken":{"kind":62,"text":"void"}},"annotations":[]},"modifiers":[{"!":"com.github.javaparser.ast.Modifier","range":{"beginLine":4,"beginColumn":2,"endLine":4,"endColumn":7},"tokenRange":{"beginToken":{"kind":47,"text":"public"},"endToken":{"kind":47,"text":"public"}},"keyword":"PUBLIC"}],"name":{"!":"com.github.javaparser.ast.expr.SimpleName","range":{"beginLine":4,"beginColumn":14,"endLine":4,"endColumn":21},"tokenRange":{"beginToken":{"kind":94,"text":"initData"},"endToken":{"kind":94,"text":"initData"}},"identifier":"initData"},"parameters":[],"thrownExceptions":[],"typeParameters":[],"annotations":[{"!":"com.github.javaparser.ast.expr.MarkerAnnotationExpr","range":{"beginLine":2,"beginColumn":1,"endLine":2,"endColumn":5},"tokenRange":{"beginToken":{"kind":107,"text":"@"},"endToken":{"kind":94,"text":"Test"}},"name":{"!":"com.github.javaparser.ast.expr.Name","range":{"beginLine":2,"beginColumn":2,"endLine":2,"endColumn":5},"tokenRange":{"beginToken":{"kind":94,"text":"Test"},"endToken":{"kind":94,"text":"Test"}},"identifier":"Test"}},{"!":"com.github.javaparser.ast.expr.SingleMemberAnnotationExpr","range":{"beginLine":3,"beginColumn":2,"endLine":3,"endColumn":14},"tokenRange":{"beginToken":{"kind":107,"text":"@"},"endToken":{"kind":98,"text":")"}},"memberValue":{"!":"com.github.javaparser.ast.expr.IntegerLiteralExpr","range":{"beginLine":3,"beginColumn":12,"endLine":3,"endColumn":13},"tokenRange":{"beginToken":{"kind":77,"text":"10"},"endToken":{"kind":77,"text":"10"}},"value":"10"},"name":{"!":"com.github.javaparser.ast.expr.Name","range":{"beginLine":3,"beginColumn":3,"endLine":3,"endColumn":10},"tokenRange":{"beginToken":{"kind":94,"text":"Priority"},"endToken":{"kind":94,"text":"Priority"}},"identifier":"Priority"}}]}],"modifiers":[],"name":{"!":"com.github.javaparser.ast.expr.SimpleName","range":{"beginLine":1,"beginColumn":7,"endLine":1,"endColumn":10},"tokenRange":{"beginToken":{"kind":94,"text":"Test"},"endToken":{"kind":94,"text":"Test"}},"identifier":"Test"},"annotations":[]}]}