{"!":"com.github.javaparser.ast.CompilationUnit","range":{"beginLine":1,"beginColumn":1,"endLine":17,"endColumn":2},"tokenRange":{"beginToken":{"kind":19,"text":"class"},"endToken":{"kind":0,"text":""}},"imports":[],"types":[{"!":"com.github.javaparser.ast.body.ClassOrInterfaceDeclaration","range":{"beginLine":1,"beginColumn":1,"endLine":17,"endColumn":2},"tokenRange":{"beginToken":{"kind":19,"text":"class"},"endToken":{"kind":100,"text":"}"}},"extendedTypes":[],"implementedTypes":[],"isInterface":"false","typeParameters":[],"members":[{"!":"com.github.javaparser.ast.body.MethodDeclaration","range":{"beginLine":2,"beginColumn":1,"endLine":15,"endColumn":2},"tokenRange":{"beginToken":{"kind":47,"text":"public"},"endToken":{"kind":100,"text":"}"}},"body":{"!":"com.github.javaparser.ast.stmt.BlockStmt","range":{"beginLine":2,"beginColumn":26,"endLine":15,"endColumn":2},"tokenRange":{"beginToken":{"kind":99,"text":"{"},"endToken":{"kind":100,"text":"}"}},"statements":[{"!":"com.github.javaparser.ast.stmt.ReturnStmt","range":{"beginLine":3,"beginColumn":3,"endLine":14,"endColumn":16},"tokenRange":{"beginToken":{"kind":49,"text":"return"},"endToken":{"kind":103,"text":";"}},"expression":{"!":"com.github.javaparser.ast.expr.MethodCallExpr","range":{"beginLine":3,"beginColumn":10,"endLine":14,"endColumn":15},"tokenRange":{"beginToken":{"kind":42,"text":"new"},"endToken":{"kind":98,"text":")"}},"arguments":[],"name":{"!":"com.github.javaparser.ast.expr.SimpleName","range":{"beginLine":14,"beginColumn":6,"endLine":14,"endColumn":13},"tokenRange":{"beginToken":{"kind":94,"text":"toString"},"endToken":{"kind":94,"text":"toString"}},"identifier":"toString"},"scope":{"!":"com.github.javaparser.ast.expr.MethodCallExpr","range":{"beginLine":3,"beginColumn":10,"endLine":13,"endColumn":16},"tokenRange":{"beginToken":{"kind":42,"text":"new"},"endToken":{"kind":98,"text":")"}},"arguments":[{"!":"com.github.javaparser.ast.expr.CharLiteralExpr","range":{"beginLine":13,"beginColumn":13,"endLine":13,"endColumn":15},"tokenRange":{"beginToken":{"kind":89,"text":"']'"},"endToken":{"kind":89,"text":"']'"}},"value":"]"}],"name":{"!":"com.github.javaparser.ast.expr.SimpleName","range":{"beginLine":13,"beginColumn":6,"endLine":13,"endColumn":11},"tokenRange":{"beginToken":{"kind":94,"text":"append"},"endToken":{"kind":94,"text":"append"}},"identifier":"append"},"scope":{"!":"com.github.javaparser.ast.expr.MethodCallExpr","range":{"beginLine":3,"beginColumn":10,"endLine":12,"endColumn":63},"tokenRange":{"beginToken":{"kind":42,"text":"new"},"endToken":{"kind":98,"text":")"}},"arguments":[{"!":"com.github.javaparser.ast.expr.FieldAccessExpr","range":{"beginLine":12,"beginColumn":42,"endLine":12,"endColumn":62},"tokenRange":{"beginToken":{"kind":56,"text":"this"},"endToken":{"kind":94,"text":"executionMinTime"}},"name":{"!":"com.github.javaparser.ast.expr.SimpleName","range":{"beginLine":12,"beginColumn":47,"endLine":12,"endColumn":62},"tokenRange":{"beginToken":{"kind":94,"text":"executionMinTime"},"endToken":{"kind":94,"text":"executionMinTime"}},"identifier":"executionMinTime"},"scope":{"!":"com.github.javaparser.ast.expr.ThisExpr","range":{"beginLine":12,"beginColumn":42,"endLine":12,"endColumn":45},"tokenRange":{"beginToken":{"kind":56,"text":"this"},"endToken":{"kind":56,"text":"this"}}}}],"name":{"!":"com.github.javaparser.ast.expr.SimpleName","range":{"beginLine":12,"beginColumn":35,"endLine":12,"endColumn":40},"tokenRange":{"beginToken":{"kind":94,"text":"append"},"endToken":{"kind":94,"text":"append"}},"identifier":"append"},"scope":{"!":"com.github.javaparser.ast.expr.MethodCallExpr","range":{"beginLine":3,"beginColumn":10,"endLine":12,"endColumn":33},"tokenRange":{"beginToken":{"kind":42,"text":"new"},"endToken":{"kind":98,"text":")"}},"arguments":[{"!":"com.github.javaparser.ast.expr.StringLiteralExpr","range":{"beginLine":12,"beginColumn":13,"endLine":12,"endColumn":32},"tokenRange":{"beginToken":{"kind":90,"text":"\",executionMinTime=\""},"endToken":{"kind":90,"text":"\",executionMinTime=\""}},"value":",executionMinTime="}],"name":{"!":"com.github.javaparser.ast.expr.SimpleName","range":{"beginLine":12,"beginColumn":6,"endLine":12,"endColumn":11},"tokenRange":{"beginToken":{"kind":94,"text":"append"},"endToken":{"kind":94,"text":"append"}},"identifier":"append"},"scope":{"!":"com.github.javaparser.ast.expr.MethodCallExpr","range":{"beginLine":3,"beginColumn":10,"endLine":11,"endColumn":63},"tokenRange":{"beginToken":{"kind":42,"text":"new"},"endToken":{"kind":98,"text":")"}},"arguments":[{"!":"com.github.javaparser.ast.expr.FieldAccessExpr","range":{"beginLine":11,"beginColumn":42,"endLine":11,"endColumn":62},"tokenRange":{"beginToken":{"kind":56,"text":"this"},"endToken":{"kind":94,"text":"executionMaxTime"}},"name":{"!":"com.github.javaparser.ast.expr.SimpleName","range":{"beginLine":11,"beginColumn":47,"endLine":11,"endColumn":62},"tokenRange":{"beginToken":{"kind":94,"text":"executionMaxTime"},"endToken":{"kind":94,"text":"executionMaxTime"}},"identifier":"executionMaxTime"},"scope":{"!":"com.github.javaparser.ast.expr.ThisExpr","range":{"beginLine":11,"beginColumn":42,"endLine":11,"endColumn":45},"tokenRange":{"beginToken":{"kind":56,"text":"this"},"endToken":{"kind":56,"text":"this"}}}}],"name":{"!":"com.github.javaparser.ast.expr.SimpleName","range":{"beginLine":11,"beginColumn":35,"endLine":11,"endColumn":40},"tokenRange":{"beginToken":{"kind":94,"text":"append"},"endToken":{"kind":94,"text":"append"}},"identifier":"append"},"scope":{"!":"com.github.javaparser.ast.expr.MethodCallExpr","range":{"beginLine":3,"beginColumn":10,"endLine":11,"endColumn":33},"tokenRange":{"beginToken":{"kind":42,"text":"new"},"endToken":{"kind":98,"text":")"}},"arguments":[{"!":"com.github.javaparser.ast.expr.StringLiteralExpr","range":{"beginLine":11,"beginColumn":13,"endLine":11,"endColumn":32},"tokenRange":{"beginToken":{"kind":90,"text":"\",executionMaxTime=\""},"endToken":{"kind":90,"text":"\",executionMaxTime=\""}},"value":",executionMaxTime="}],"name":{"!":"com.github.javaparser.ast.expr.SimpleName","range":{"beginLine":11,"beginColumn":6,"endLine":11,"endColumn":11},"tokenRange":{"beginToken":{"kind":94,"text":"append"},"endToken":{"kind":94,"text":"append"}},"identifier":"append"},"scope":{"!":"com.github.javaparser.ast.expr.MethodCallExpr","range":{"beginLine":3,"beginColumn":10,"endLine":10,"endColumn":68},"tokenRange":{"beginToken":{"kind":42,"text":"new"},"endToken":{"kind":98,"text":")"}},"arguments":[{"!":"com.github.javaparser.ast.expr.MethodCallExpr","range":{"beginLine":10,"beginColumn":42,"endLine":10,"endColumn":67},"tokenRange":{"beginToken":{"kind":56,"text":"this"},"endToken":{"kind":98,"text":")"}},"arguments":[],"name":{"!":"com.github.javaparser.ast.expr.SimpleName","range":{"beginLine":10,"beginColumn":47,"endLine":10,"endColumn":65},"tokenRange":{"beginToken":{"kind":94,"text":"getExecutionAvgTime"},"endToken":{"kind":94,"text":"getExecutionAvgTime"}},"identifier":"getExecutionAvgTime"},"scope":{"!":"com.github.javaparser.ast.expr.ThisExpr","range":{"beginLine":10,"beginColumn":42,"endLine":10,"endColumn":45},"tokenRange":{"beginToken":{"kind":56,"text":"this"},"endToken":{"kind":56,"text":"this"}}}}],"name":{"!":"com.github.javaparser.ast.expr.SimpleName","range":{"beginLine":10,"beginColumn":35,"endLine":10,"endColumn":40},"tokenRange":{"beginToken":{"kind":94,"text":"append"},"endToken":{"kind":94,"text":"append"}},"identifier":"append"},"scope":{"!":"com.github.javaparser.ast.expr.MethodCallExpr","range":{"beginLine":3,"beginColumn":10,"endLine":10,"endColumn":33},"tokenRange":{"beginToken":{"kind":42,"text":"new"},"endToken":{"kind":98,"text":")"}},"arguments":[{"!":"com.github.javaparser.ast.expr.StringLiteralExpr","range":{"beginLine":10,"beginColumn":13,"endLine":10,"endColumn":32},"tokenRange":{"beginToken":{"kind":90,"text":"\",executionAvgTime=\""},"endToken":{"kind":90,"text":"\",executionAvgTime=\""}},"value":",executionAvgTime="}],"name":{"!":"com.github.javaparser.ast.expr.SimpleName","range":{"beginLine":10,"beginColumn":6,"endLine":10,"endColumn":11},"tokenRange":{"beginToken":{"kind":94,"text":"append"},"endToken":{"kind":94,"text":"append"}},"identifier":"append"},"scope":{"!":"com.github.javaparser.ast.expr.MethodCallExpr","range":{"beginLine":3,"beginColumn":10,"endLine":9,"endColumn":65},"tokenRange":{"beginToken":{"kind":42,"text":"new"},"endToken":{"kind":98,"text":")"}},"arguments":[{"!":"com.github.javaparser.ast.expr.FieldAccessExpr","range":{"beginLine":9,"beginColumn":43,"endLine":9,"endColumn":64},"tokenRange":{"beginToken":{"kind":56,"text":"this"},"endToken":{"kind":94,"text":"executionRowCount"}},"name":{"!":"com.github.javaparser.ast.expr.SimpleName","range":{"beginLine":9,"beginColumn":48,"endLine":9,"endColumn":64},"tokenRange":{"beginToken":{"kind":94,"text":"executionRowCount"},"endToken":{"kind":94,"text":"executionRowCount"}},"identifier":"executionRowCount"},"scope":{"!":"com.github.javaparser.ast.expr.ThisExpr","range":{"beginLine":9,"beginColumn":43,"endLine":9,"endColumn":46},"tokenRange":{"beginToken":{"kind":56,"text":"this"},"endToken":{"kind":56,"text":"this"}}}}],"name":{"!":"com.github.javaparser.ast.expr.SimpleName","range":{"beginLine":9,"beginColumn":36,"endLine":9,"endColumn":41},"tokenRange":{"beginToken":{"kind":94,"text":"append"},"endToken":{"kind":94,"text":"append"}},"identifier":"append"},"scope":{"!":"com.github.javaparser.ast.expr.MethodCallExpr","range":{"beginLine":3,"beginColumn":10,"endLine":9,"endColumn":34},"tokenRange":{"beginToken":{"kind":42,"text":"new"},"endToken":{"kind":98,"text":")"}},"arguments":[{"!":"com.github.javaparser.ast.expr.StringLiteralExpr","range":{"beginLine":9,"beginColumn":13,"endLine":9,"endColumn":33},"tokenRange":{"beginToken":{"kind":90,"text":"\",executionRowCount=\""},"endToken":{"kind":90,"text":"\",executionRowCount=\""}},"value":",executionRowCount="}],"name":{"!":"com.github.javaparser.ast.expr.SimpleName","range":{"beginLine":9,"beginColumn":6,"endLine":9,"endColumn":11},"tokenRange":{"beginToken":{"kind":94,"text":"append"},"endToken":{"kind":94,"text":"append"}},"identifier":"append"},"scope":{"!":"com.github.javaparser.ast.expr.MethodCallExpr","range":{"beginLine":3,"beginColumn":10,"endLine":8,"endColumn":59},"tokenRange":{"beginToken":{"kind":42,"text":"new"},"endToken":{"kind":98,"text":")"}},"arguments":[{"!":"com.github.javaparser.ast.expr.FieldAccessExpr","range":{"beginLine":8,"beginColumn":40,"endLine":8,"endColumn":58},"tokenRange":{"beginToken":{"kind":56,"text":"this"},"endToken":{"kind":94,"text":"executionCount"}},"name":{"!":"com.github.javaparser.ast.expr.SimpleName","range":{"beginLine":8,"beginColumn":45,"endLine":8,"endColumn":58},"tokenRange":{"beginToken":{"kind":94,"text":"executionCount"},"endToken":{"kind":94,"text":"executionCount"}},"identifier":"executionCount"},"scope":{"!":"com.github.javaparser.ast.expr.ThisExpr","range":{"beginLine":8,"beginColumn":40,"endLine":8,"endColumn":43},"tokenRange":{"beginToken":{"kind":56,"text":"this"},"endToken":{"kind":56,"text":"this"}}}}],"name":{"!":"com.github.javaparser.ast.expr.SimpleName","range":{"beginLine":8,"beginColumn":33,"endLine":8,"endColumn":38},"tokenRange":{"beginToken":{"kind":94,"text":"append"},"endToken":{"kind":94,"text":"append"}},"identifier":"append"},"scope":{"!":"com.github.javaparser.ast.expr.MethodCallExpr","range":{"beginLine":3,"beginColumn":10,"endLine":8,"endColumn":31},"tokenRange":{"beginToken":{"kind":42,"text":"new"},"endToken":{"kind":98,"text":")"}},"arguments":[{"!":"com.github.javaparser.ast.expr.StringLiteralExpr","range":{"beginLine":8,"beginColumn":13,"endLine":8,"endColumn":30},"tokenRange":{"beginToken":{"kind":90,"text":"\",executionCount=\""},"endToken":{"kind":90,"text":"\",executionCount=\""}},"value":",executionCount="}],"name":{"!":"com.github.javaparser.ast.expr.SimpleName","range":{"beginLine":8,"beginColumn":6,"endLine":8,"endColumn":11},"tokenRange":{"beginToken":{"kind":94,"text":"append"},"endToken":{"kind":94,"text":"append"}},"identifier":"append"},"scope":{"!":"com.github.javaparser.ast.expr.MethodCallExpr","range":{"beginLine":3,"beginColumn":10,"endLine":7,"endColumn":57},"tokenRange":{"beginToken":{"kind":42,"text":"new"},"endToken":{"kind":98,"text":")"}},"arguments":[{"!":"com.github.javaparser.ast.expr.FieldAccessExpr","range":{"beginLine":7,"beginColumn":39,"endLine":7,"endColumn":56},"tokenRange":{"beginToken":{"kind":56,"text":"this"},"endToken":{"kind":94,"text":"cachePutCount"}},"name":{"!":"com.github.javaparser.ast.expr.SimpleName","range":{"beginLine":7,"beginColumn":44,"endLine":7,"endColumn":56},"tokenRange":{"beginToken":{"kind":94,"text":"cachePutCount"},"endToken":{"kind":94,"text":"cachePutCount"}},"identifier":"cachePutCount"},"scope":{"!":"com.github.javaparser.ast.expr.ThisExpr","range":{"beginLine":7,"beginColumn":39,"endLine":7,"endColumn":42},"tokenRange":{"beginToken":{"kind":56,"text":"this"},"endToken":{"kind":56,"text":"this"}}}}],"name":{"!":"com.github.javaparser.ast.expr.SimpleName","range":{"beginLine":7,"beginColumn":32,"endLine":7,"endColumn":37},"tokenRange":{"beginToken":{"kind":94,"text":"append"},"endToken":{"kind":94,"text":"append"}},"identifier":"append"},"scope":{"!":"com.github.javaparser.ast.expr.MethodCallExpr","range":{"beginLine":3,"beginColumn":10,"endLine":7,"endColumn":30},"tokenRange":{"beginToken":{"kind":42,"text":"new"},"endToken":{"kind":98,"text":")"}},"arguments":[{"!":"com.github.javaparser.ast.expr.StringLiteralExpr","range":{"beginLine":7,"beginColumn":13,"endLine":7,"endColumn":29},"tokenRange":{"beginToken":{"kind":90,"text":"\",cachePutCount=\""},"endToken":{"kind":90,"text":"\",cachePutCount=\""}},"value":",cachePutCount="}],"name":{"!":"com.github.javaparser.ast.expr.SimpleName","range":{"beginLine":7,"beginColumn":6,"endLine":7,"endColumn":11},"tokenRange":{"beginToken":{"kind":94,"text":"append"},"endToken":{"kind":94,"text":"append"}},"identifier":"append"},"scope":{"!":"com.github.javaparser.ast.expr.MethodCallExpr","range":{"beginLine":3,"beginColumn":10,"endLine":6,"endColumn":59},"tokenRange":{"beginToken":{"kind":42,"text":"new"},"endToken":{"kind":98,"text":")"}},"arguments":[{"!":"com.github.javaparser.ast.expr.FieldAccessExpr","range":{"beginLine":6,"beginColumn":40,"endLine":6,"endColumn":58},"tokenRange":{"beginToken":{"kind":56,"text":"this"},"endToken":{"kind":94,"text":"cacheMissCount"}},"name":{"!":"com.github.javaparser.ast.expr.SimpleName","range":{"beginLine":6,"beginColumn":45,"endLine":6,"endColumn":58},"tokenRange":{"beginToken":{"kind":94,"text":"cacheMissCount"},"endToken":{"kind":94,"text":"cacheMissCount"}},"identifier":"cacheMissCount"},"scope":{"!":"com.github.javaparser.ast.expr.ThisExpr","range":{"beginLine":6,"beginColumn":40,"endLine":6,"endColumn":43},"tokenRange":{"beginToken":{"kind":56,"text":"this"},"endToken":{"kind":56,"text":"this"}}}}],"name":{"!":"com.github.javaparser.ast.expr.SimpleName","range":{"beginLine":6,"beginColumn":33,"endLine":6,"endColumn":38},"tokenRange":{"beginToken":{"kind":94,"text":"append"},"endToken":{"kind":94,"text":"append"}},"identifier":"append"},"scope":{"!":"com.github.javaparser.ast.expr.MethodCallExpr","range":{"beginLine":3,"beginColumn":10,"endLine":6,"endColumn":31},"tokenRange":{"beginToken":{"kind":42,"text":"new"},"endToken":{"kind":98,"text":")"}},"arguments":[{"!":"com.github.javaparser.ast.expr.StringLiteralExpr","range":{"beginLine":6,"beginColumn":13,"endLine":6,"endColumn":30},"tokenRange":{"beginToken":{"kind":90,"text":"\",cacheMissCount=\""},"endToken":{"kind":90,"text":"\",cacheMissCount=\""}},"value":",cacheMissCount="}],"name":{"!":"com.github.javaparser.ast.expr.SimpleName","range":{"beginLine":6,"beginColumn":6,"endLine":6,"endColumn":11},"tokenRange":{"beginToken":{"kind":94,"text":"append"},"endToken":{"kind":94,"text":"append"}},"identifier":"append"},"scope":{"!":"com.github.javaparser.ast.expr.MethodCallExpr","range":{"beginLine":3,"beginColumn":10,"endLine":5,"endColumn":57},"tokenRange":{"beginToken":{"kind":42,"text":"new"},"endToken":{"kind":98,"text":")"}},"arguments":[{"!":"com.github.javaparser.ast.expr.FieldAccessExpr","range":{"beginLine":5,"beginColumn":39,"endLine":5,"endColumn":56},"tokenRange":{"beginToken":{"kind":56,"text":"this"},"endToken":{"kind":94,"text":"cacheHitCount"}},"name":{"!":"com.github.javaparser.ast.expr.SimpleName","range":{"beginLine":5,"beginColumn":44,"endLine":5,"endColumn":56},"tokenRange":{"beginToken":{"kind":94,"text":"cacheHitCount"},"endToken":{"kind":94,"text":"cacheHitCount"}},"identifier":"cacheHitCount"},"scope":{"!":"com.github.javaparser.ast.expr.ThisExpr","range":{"beginLine":5,"beginColumn":39,"endLine":5,"endColumn":42},"tokenRange":{"beginToken":{"kind":56,"text":"this"},"endToken":{"kind":56,"text":"this"}}}}],"name":{"!":"com.github.javaparser.ast.expr.SimpleName","range":{"beginLine":5,"beginColumn":32,"endLine":5,"endColumn":37},"tokenRange":{"beginToken":{"kind":94,"text":"append"},"endToken":{"kind":94,"text":"append"}},"identifier":"append"},"scope":{"!":"com.github.javaparser.ast.expr.MethodCallExpr","range":{"beginLine":3,"beginColumn":10,"endLine":5,"endColumn":30},"tokenRange":{"beginToken":{"kind":42,"text":"new"},"endToken":{"kind":98,"text":")"}},"arguments":[{"!":"com.github.javaparser.ast.expr.StringLiteralExpr","range":{"beginLine":5,"beginColumn":13,"endLine":5,"endColumn":29},"tokenRange":{"beginToken":{"kind":90,"text":"\"[cacheHitCount=\""},"endToken":{"kind":90,"text":"\"[cacheHitCount=\""}},"value":"[cacheHitCount="}],"name":{"!":"com.github.javaparser.ast.expr.SimpleName","range":{"beginLine":5,"beginColumn":6,"endLine":5,"endColumn":11},"tokenRange":{"beginToken":{"kind":94,"text":"append"},"endToken":{"kind":94,"text":"append"}},"identifier":"append"},"scope":{"!":"com.github.javaparser.ast.expr.MethodCallExpr","range":{"beginLine":3,"beginColumn":10,"endLine":4,"endColumn":30},"tokenRange":{"beginToken":{"kind":42,"text":"new"},"endToken":{"kind":98,"text":")"}},"arguments":[{"!":"com.github.javaparser.ast.expr.StringLiteralExpr","range":{"beginLine":4,"beginColumn":13,"endLine":4,"endColumn":29},"tokenRange":{"beginToken":{"kind":90,"text":"\"QueryStatistics\""},"endToken":{"kind":90,"text":"\"QueryStatistics\""}},"value":"QueryStatistics"}],"name":{"!":"com.github.javaparser.ast.expr.SimpleName","range":{"beginLine":4,"beginColumn":6,"endLine":4,"endColumn":11},"tokenRange":{"beginToken":{"kind":94,"text":"append"},"endToken":{"kind":94,"text":"append"}},"identifier":"append"},"scope":{"!":"com.github.javaparser.ast.expr.ObjectCreationExpr","range":{"beginLine":3,"beginColumn":10,"endLine":3,"endColumn":28},"tokenRange":{"beginToken":{"kind":42,"text":"new"},"endToken":{"kind":98,"text":")"}},"arguments":[],"type":{"!":"com.github.javaparser.ast.type.ClassOrInterfaceType","range":{"beginLine":3,"beginColumn":14,"endLine":3,"endColumn":26},"tokenRange":{"beginToken":{"kind":94,"text":"StringBuilder"},"endToken":{"kind":94,"text":"StringBuilder"}},"name":{"!":"com.github.javaparser.ast.expr.SimpleName","range":{"beginLine":3,"beginColumn":14,"endLine":3,"endColumn":26},"tokenRange":{"beginToken":{"kind":94,"text":"StringBuilder"},"endToken":{"kind":94,"text":"StringBuilder"}},"identifier":"StringBuilder"},"annotations":[]}}}}}}}}}}}}}}}}}}}}}}]},"type":{"!":"com.github.javaparser.ast.type.ClassOrInterfaceType","range":{"beginLine":2,"beginColumn":8,"endLine":2,"endColumn":13},"tokenRange":{"beginToken":{"kind":94,"text":"String"},"endToken":{"kind":94,"text":"String"}},"name":{"!":"com.github.javaparser.ast.expr.SimpleName","range":{"beginLine":2,"beginColumn":8,"endLine":2,"endColumn":13},"tokenRange":{"beginToken":{"kind":94,"text":"String"},"endToken":{"kind":94,"text":"String"}},"identifier":"String"},"annotations":[]},"modifiers":[{"!":"com.github.javaparser.ast.Modifier","range":{"beginLine":2,"beginColumn":1,"endLine":2,"endColumn":6},"tokenRange":{"beginToken":{"kind":47,"text":"public"},"endToken":{"kind":47,"text":"public"}},"keyword":"PUBLIC"}],"name":{"!":"com.github.javaparser.ast.expr.SimpleName","range":{"beginLine":2,"beginColumn":15,"endLine":2,"endColumn":22},"tokenRange":{"beginToken":{"kind":94,"text":"toString"},"endToken":{"kind":94,"text":"toString"}},"identifier":"toString"},"parameters":[],"thrownExceptions":[],"typeParameters":[],"annotations":[]}],"modifiers":[],"name":{"!":"com.github.javaparser.ast.expr.SimpleName","range":{"beginLine":1,"beginColumn":7,"endLine":1,"endColumn":10},"tokenRange":{"beginToken":{"kind":94,"text":"Test"},"endToken":{"kind":94,"text":"Test"}},"identifier":"Test"},"annotations":[]}]}